textmatch-1.2.0.dist-info/METADATA
textmatch-1.2.0.dist-info/WHEEL
textmatch-1.2.0.dist-info/entry_points.txt
textmatch-1.2.0.dist-info/licenses/LICENCE
textmatch/__init__.py
textmatch/ignored-titles.txt
textmatch/methods/bilenko.py
textmatch/methods/jaro.py
textmatch/methods/levenshtein.py
textmatch/methods/metaphone.py
textmatch/py.typed
textmatch/textmatch.py
textmatch/typings.py
textmatch-1.2.0.dist-info/RECORD
