Metadata-Version: 2.4
Name: textmatch
Version: 1.2.0
Summary: Find fuzzy matches between datasets.
Author-Email: Max Harlow <contact@maxharlow.com>
License-Expression: Apache-2.0
Project-URL: source, https://github.com/maxharlow/textmatch
Requires-Python: ==3.14.*
Requires-Dist: polars[pandas,pyarrow]==1.37.*
Requires-Dist: polars-distance==0.5.*
Requires-Dist: colorama==0.4.*
Requires-Dist: unidecode==1.4.*
Requires-Dist: doublemetaphone==1.2.*
Requires-Dist: dedupe==3.0.*
